highway_star/__init__.py
highway_star/pipeline.py
highway_star/filtering/__init__.py
highway_star/preprocessing/__init__.py
highway_star/preprocessing/biography_preprocessor.py
highway_star/scrapping/__init__.py
highway_star/scrapping/wikipedia_scraper.py
highway_star/visualizing/__init__.py
highway_star/visualizing/visualizer.py
highway_star-0.0.8.2.dist-info/METADATA
highway_star-0.0.8.2.dist-info/WHEEL
highway_star-0.0.8.2.dist-info/top_level.txt
highway_star-0.0.8.2.dist-info/RECORD
