Metadata-Version: 2.1
Name: highway-star
Version: 0.0.8.2
Summary: A library to scrap content from wikipedia categories
Home-page: https://github.com/matheo-daly/highway_star
Author: Mathéo Daly
Author-email: matheodaly.md@gmail.com
License: UNKNOWN
Platform: UNKNOWN
Classifier: Programming Language :: Python :: 3
Classifier: License :: OSI Approved :: MIT License
Classifier: Operating System :: OS Independent
Requires-Python: >=3.6
Requires-Dist: beautifulsoup4
Requires-Dist: requests
Requires-Dist: regex
Requires-Dist: rich
Requires-Dist: pandas
Requires-Dist: setuptools
Requires-Dist: SPARQLWrapper
Requires-Dist: gensim
Requires-Dist: nltk
Requires-Dist: spacy
Requires-Dist: prefixspan
